{
    "data": [
        {
            "estabelecimento":      "Local Teste 1",
            "tipo":                 "Supermercado",
            "endereco":             "Rua Teste 1",
            "cidade":               "Ribeirao Preto",
            "estado":               "SP",
            "imagem":               "./img/0001.png"
        },
        {
            "estabelecimento":      "Local Teste 2",
            "tipo":                 "Cinema",
            "endereco":             "Rua Teste 2",
            "cidade":               "Orlandia",
            "estado":               "SP",
            "imagem":               "./img/0002.png"
        },
         {
            "estabelecimento":      "Local Teste 3",
            "tipo":                 "Lanchonete",
            "endereco":             "Rua Teste 3",
            "cidade":               "Sertaozinho",
            "estado":               "SP",
            "imagem":               "./img/0003.png"
        }
    ]
}